<GroupList>	
	<Include Path="Common.xml"/>
	<GridContainer FillColor="#6e7887" Height="40" HorizontalAlignment="Stretch">
		<Columns>
			<Column Width="Auto"/>
			<Column Width="1*"/>
		</Columns>
		<Image Column="0" Size="25,25" ColorMask="#FF1200" VerticalAlignment="Center" Margin="5" Name="Image"/>
		<Image ColumnSpan="2" Name="Validation" Alpha="0.25" ColorMask="#FF0000" Visible="false"/>
		<Text Column="1" Name="ParamName" Text="Nagyonszép dummyk"  TextAlignH="Left" MarginLeft="5" FontSize="16"/>
	</GridContainer>
	<FlowContainer Name="TypeList"/>
	<RadioGroupLogical Name="RadioGroup"/>
</GroupList>