<?xml version="1.0" encoding="UTF-8" standalone="yes" ?>
<Window Size="300,200">
	<Constants>
		<MaxKoponyaCountLarge Type="int" Value="4"/>
		<MaxKoponyaCountSmall Type="int" Value="5"/>
	</Constants>
	
	<FlowContainer Width="300" VerticalAlignment="bottom">	
		<Include Path="Windows/Objectives/ExtraObjectives.xml"/>
		<Text Name="Title" Pos="17,4" Size="280,32" Style="Headline_Large_Color_Glow" TextAlignH="left" TextAlignV="center" Text="mission.MaelstromOfCarnage.name"/>
		<FlowContainer Name="HuntMission" MarginTop="4" MarginBottom="0" TextAlignV="bottom"
		Width="300"
		BackgroundTopSize="36"
		BackgroundBotSize="100"
		BackgroundTopImage="UI/objectives/objectives_backgroundTop.tga"
		BackgroundMidImage="UI/objectives/objectives_backgroundMiddle.tga"
		BackgroundBotImage="UI/objectives/objectives_backgroundBottom.tga"
		>
			<Dummy Height="18"/>
			<FlowContainer Name="Objective" Pos="14,0" Width="280">
				<Container Pos="0,0" Size="280,52" MarginTop="5" MarginBottom="5">
					<Image Name="RatingBack" Pos="189,0" Size="84,52" Image="UI/OpenWorld/icon_challengeWhite.tga"/>					
					<TextBox Pos="2,2" Size="176,55" UseSlider="0" Style="Text_Large_Light" TextAlignH="left" TextAlignV="center" Text="mission.MaelstromOfCarnage.score"/>
					<Text Name="CurrentScore" Pos="194,9" Size="72,36" Style="Clue_Cogitator_Text" TextAlignH="center" TextAlignV="center" FontSize="28" BiggerFontSize="30" Color="#ededed" Sharpness="0.5" Text="_113"/>
				</Container>
				<Image Name="Line1" Pos="0,1" Size="266,4" Image="UI/Assignment/assignment_bigline.tga"/>
				<Container Pos="0,0" MarginTop="6" Size="280,30">
					<Text Name="Remaining" Visible="1" Pos="8,0" Size="320,30" Style="Text_Normal_Light" TextAlignH="left" TextAlignV="center" Text="_6969"/>
				</Container>	
				<Container MarginTop="6">
					<CheckBox Name="Objective1_Off" Size="24,24" Style="Text_Normal_Light" Color="#54f1eb" TextAlignH="left" TextAlignV="center" ImageUnchecked="UI/Objectives/objectives_checkboxOff.tga" Checked="0" MouseSenseEnabled="0"/>
					<CheckBox Name="Objective1_On" Size="24,24" Style="Text_Normal_Light" TextAlignH="left" TextAlignV="center" ImageChecked="UI/Objectives/objectives_checkboxOn.tga" Checked="1" MouseSenseEnabled="0"/>
					<TextBox Name="ObjectiveText" Pos="30,1" Width="250" UseSlider="0" Style="Text_Normal_Color" VerticalAlignment="top" TextAlignH="left" TextAlignV="top" Text="mission.MaelstromOfCarnage.objective1"/>
				</Container>
				<Container MarginTop="6">
					<CheckBox Name="Objective2_Off" Size="24,24" Style="Text_Normal_Light" Color="#54f1eb" TextAlignH="left" TextAlignV="center" ImageUnchecked="UI/Objectives/objectives_checkboxOff.tga" Checked="0" MouseSenseEnabled="0"/>
					<CheckBox Name="Objective2_On" Size="24,24" Style="Text_Normal_Light" TextAlignH="left" TextAlignV="center" ImageChecked="UI/Objectives/objectives_checkboxOn.tga" Checked="1" MouseSenseEnabled="0"/>
					<TextBox Name="Objective2Text" Pos="30,2" Width="250" UseSlider="0" Style="Text_Normal_Color" VerticalAlignment="top" TextAlignH="left" TextAlignV="top" Text="mission.MaelstromOfCarnage.objective2"/>
				</Container>
			</FlowContainer>	

			<Container Pos="0,0" Size="284,42" MarginTop="6" MarginBottom="19">
				<Image Name="Line2" Pos="14,1" Size="266,4" Image="UI/Assignment/assignment_bigline.tga"/>	
				<Text Name="AllowedDeath" Pos="17,10" Size="130,30" Style="Text_Normal_Light" TextAlignH="left" TextAlignV="center" Text="mission.common.allowed_death"/>
				<Container Name="SkullsLarge" Pos="156,11" Size="128,32">
					<FlowContainer Horizontal="1" HorizontalAlignment="right">
						<Loop Count="@MaxKoponyaCountLarge" Variable="$X$">
							<Image Name="LifeLarge$X$" Size="32,32" Image="UI/Objectives/objectives_lifeOn.tga"/>
						</Loop>
					</FlowContainer>
				</Container>
				<Container Name="SkullsSmall" Pos="164,13" Size="120,32" Visible="0">
					<FlowContainer Horizontal="1" HorizontalAlignment="right">
						<Loop Count="@MaxKoponyaCountSmall" Variable="$X$">
							<Image Name="LifeSmall$X$" Size="24,24" Image="UI/Objectives/objectives_lifeOn.tga"/>
						</Loop>
					</FlowContainer>
				</Container>
			</Container>			

		</FlowContainer>
	</FlowContainer>
	
	<Effect Name="CountdownEffect" GuiAlign="center"
		Size="1920,1080"
		Pos="-1577,-656"
		Effect="UI\Orbital_strike_countdown\orbital_strike_countdown.N2E"
		Loop="0"
		MouseSenseEnabled="0"
	/>
</Window>

	
	
	

