<?xml version="1.0" encoding="UTF-8" standalone="yes" ?>
<Window Pos="461,95" GuiAlign="center" OpenTransition="Fast" CloseTransition="Fast">
	<Include Path="Windows/Styles.xml"/>
	
	<Constants>
		<Visible Type="int" Value="1"/>
		<EventProgressBarLength Type="int" Value="440"/>	
		<MaxRewardCount Type="int" Value="4"/>
		
		<MultiProgress3 Type="int" Value="3"/>			
		<MultiProgress3Bar Type="int" Value="140"/>	
	</Constants>
	
	<Container>
		<Image Name="Bg"
			Pos="0,0"
			Size="996,840"
			Image="placeholder.tga"
		/>
		<Image
			Pos="0,0"
			Size="996,840"
			Image="UI/common/Options/options_background2_resized.tga"
		/>
		<Text Name="EventTitle"
			Pos="148,98"
			Size="706,30"
			Style="Headline_Large_Light_Glow"
			TextAlignH="center"
			TextAlignV="center"
			Text="openworld.GUI.worldevent.title"
		/>
		<Text Name="EventSubtitle"
			Pos="148,140"
			Size="706,30"
			Style="Headline_Large_Light_Glow"
			TextAlignH="center"
			TextAlignV="center"
			Text="WorldEvent.BlackLegionHunt.subtitle"
		/>

		<Container Name="Left">
			<ScrollableContainer Pos="44,190" Size="454,580" UseLeftStick="1" UseRightStick="0">
			<FlowContainer Width="430">
					<TextBox Name="EventText"
						Style="Text_Normal_Light"
						Width="430"
						Text="_EventText"
						MouseSenseEnabled="0"
					/>
					<TextBox Name="EventObjective"
						Style="Text_Normal_Light"
						MarginTop="14"
						Width="430"
						Text="_EventObjective"
						MouseSenseEnabled="0"
					/>
			</FlowContainer>
			</ScrollableContainer>
		</Container>

		<Container Name="Right">
			<ScrollableContainer Pos="504,190" Size="464,580" UseLeftStick="0" UseRightStick="1">
				<FlowContainer  Width="436">
						
					<FlowContainer Name="Season" Width="480" MarginBottom="10">
						<TextBox Name="SeasonText"
							Style="Text_Normal_Light"
							Width="436"
							Text="_EventText"
							MouseSenseEnabled="0"
						/>
						<TextBox Name="SeasonNote"
							Style="Text_Normal_Light"
							MarginTop="14"
							Width="436"
							Text="_EventObjective"
							MouseSenseEnabled="0"
						/>
					</FlowContainer>
					
					<FlowContainer Name="WorldEventProgress" Width="480" MarginBottom="10">
						<Text
							Style="Headline_Large_Light"
							Width="436"
							TextAlignH="Left"
							Text="openworld.GUI.worldevent.tasks"
							MouseSenseEnabled="0"
						/>
						<Image
							Pos="0,5"
							Size="436,4"
							Image="UI/Assignment/assignment_bigline.tga"
							MouseSenseEnabled="0"
						/>
						<TextBox Name="EventProgressText"
							Style="Text_Normal_Light"
							Width="436"
							MarginTop="15"
							Text="_WorldEventObjective"
							MouseSenseEnabled="0"
						/>
						<Container Size="436,38" MarginBottom="-6">
							<FlowContainer Name="EventProgressTooltip"
								MarginTop="8"
								Height="20"
								Horizontal="1"
								BackgroundTopSize="8"
								BackgroundBotSize="8"
								BackgroundTopImage="UI/objectives/objectives_barBgLeft.tga"
								BackgroundMidImage="UI/objectives/objectives_barBgMiddle.tga"
								BackgroundBotImage="UI/objectives/objectives_barBgRight.tga"
								InitPopup="rightcenter,leftcenter"
								Tooltip="_999/999"
							>
								<Dummy Name="EventProgressBg" Height="20" Width="@EventProgressBarLength" MouseSenseEnabled="0"/>
							</FlowContainer>
							<FlowContainer
								MarginTop="8"
								Height="20"
								Horizontal="1"
								BackgroundTopSize="8"
								BackgroundBotSize="8"
								BackgroundTopImage="UI/CharacterSheet/frame_attribute_barLeft.tga"
								BackgroundMidImage="UI/CharacterSheet/frame_attribute_barMiddle.tga"
								BackgroundBotImage="UI/CharacterSheet/frame_attribute_barRight.tga"
								MouseSenseEnabled="0"
							>
								<Dummy Name="EventProgressBar" Height="20" Width="@EventProgressBarLength" MouseSenseEnabled="0"/>
							</FlowContainer>
							<Container Name="RewardMarker3" Visible="1">
								<Loop Count="3" Variable="$Y$">
									<Image Name="Reward3$Y$Marker"
										MarginTop="22"
										MarginLeft="-2"
										Size="12,12"
										Image="UI/OpenWorld/starmap_barMarker.tga"
										MouseSenseEnabled="0"
										_IgnoreScissor="1"
									/>
								</Loop>
							</Container>
						</Container>
						<Loop Count="@MaxRewardCount" Variable="$X$">							
							<Container Name="Reward$X$" MarginBottom="2" Visible="0">
								<Image Name="RewardIcon$X$"
									Pos="3,0"
									MarginTop="10"
									Size="45,45"
									Image="UI/common/Events/event_skulls_reward.tga"
									MouseSenseEnabled="0"
								/>	
								<Text Name="RewardTask$X$"
									Style="Text_Normal_Dark"
									Pos="58,10"
									Size="400,22"
									TextAlignV="center"
									TextAlignH="left"
									Text="_RewardDesc"
									MouseSenseEnabled="0"
								/>
								<Text Name="RewardReward$X$"
									Style="Text_Normal_Light"
									Pos="58,33"
									Size="400,22"
									TextAlignV="center"
									TextAlignH="left"
									Text="_RewardDesc"
									MouseSenseEnabled="0"
								/>
							</Container>
						</Loop>
					</FlowContainer>
					
					<FlowContainer Name="WorldEventCabalProgress" Width="480" MarginBottom="10">
						<Text
							Style="Headline_Large_Light"
							MarginTop="15"
							Width="436"
							TextAlignH="Left"
							Text="openworld.GUI.worldevent.cabaltasks"
							MouseSenseEnabled="0"
						/>
						<Image
							Pos="0,5"
							Size="436,4"
							Image="UI/Assignment/assignment_bigline.tga"
							MouseSenseEnabled="0"
						/>
						<TextBox Name="EventCabalProgressText"
							Style="Text_Normal_Light"
							Width="436"
							MarginTop="15"
							Text="_WorldEventCommunityObjective"
							MouseSenseEnabled="0"
						/>
						<Container Size="436,38"  MarginBottom="-6">
							<FlowContainer Name="EventCabalProgressTooltip"
								MarginTop="8"
								Height="20"
								Horizontal="1"
								BackgroundTopSize="8"
								BackgroundBotSize="8"
								BackgroundTopImage="UI/objectives/objectives_barBgLeft.tga"
								BackgroundMidImage="UI/objectives/objectives_barBgMiddle.tga"
								BackgroundBotImage="UI/objectives/objectives_barBgRight.tga"
								InitPopup="rightcenter,leftcenter"
								Tooltip="_999/999"
							>
								<Dummy Name="EventCabalProgressBg" Height="20" Width="@EventProgressBarLength" MouseSenseEnabled="0"/>
							</FlowContainer>
							<FlowContainer
								MarginTop="8"
								Height="20"
								Horizontal="1"
								BackgroundTopSize="8"
								BackgroundBotSize="8"
								BackgroundTopImage="UI/CharacterSheet/frame_attribute_barLeft.tga"
								BackgroundMidImage="UI/CharacterSheet/frame_attribute_barMiddle.tga"
								BackgroundBotImage="UI/CharacterSheet/frame_attribute_barRight.tga"
								MouseSenseEnabled="0"
							>
								<Dummy Name="EventCabalProgressBar" Height="20" Width="@EventProgressBarLength" MouseSenseEnabled="0"/>
							</FlowContainer>
							<Container Name="CabalRewardMarker3" Visible="0">
								<Loop Count="3" Variable="$Y$" Offset="144,0">
									<Image Name="CabalReward3$Y$Marker"
										Pos="139,26"
										Size="12,12"
										Image="UI/OpenWorld/starmap_barMarker.tga"
										MouseSenseEnabled="0"
									/>
								</Loop>
							</Container>
						</Container>					
						<Loop Count="@MaxRewardCount" Variable="$X$">
							<Container Name="CabalReward$X$" MarginBottom="2" Visible="0">
								<Image Name="CabalRewardIcon$X$"
									Pos="3,0"
									MarginTop="10"
									Size="45,45"
									Image="UI/common/Events/event_skulls_reward.tga"
									MouseSenseEnabled="0"
								/>	
								<Text Name="CabalRewardTask$X$"
									Style="Text_Normal_Dark"
									Pos="58,10"
									Size="400,22"
									TextAlignV="center"
									TextAlignH="left"
									Text="_RewardDesc"
									MouseSenseEnabled="0"
								/>
								<Text Name="CabalRewardReward$X$"
									Style="Text_Normal_Light"
									Pos="58,33"
									Size="400,22"
									TextAlignV="center"
									TextAlignH="left"
									Text="_RewardDesc"
									MouseSenseEnabled="0"
								/>
							</Container>
						</Loop>
					</FlowContainer>
					
					<FlowContainer Name="WorldEventCommunityProgress" Width="480">
						<Text
							Style="Headline_Large_Light"
							MarginTop="15"
							Width="436"
							TextAlignH="Left"
							Text="openworld.GUI.worldevent.communitytasks"
							MouseSenseEnabled="0"
						/>
						<Image
							Pos="0,5"
							Size="436,4"
							Image="UI/Assignment/assignment_bigline.tga"
							MouseSenseEnabled="0"
						/>
						<TextBox Name="EventCommunityProgressText"
							Style="Text_Normal_Light"
							Width="436"
							MarginTop="15"
							Text="_WorldEventCommunityObjective"
							MouseSenseEnabled="0"
						/>
						<Container Name="EventCommunityProgress" Size="436,38" Visible="0">
								<FlowContainer
									MarginTop="8"
									Height="20"
									Horizontal="1"
									BackgroundTopSize="8"
									BackgroundBotSize="8"
									BackgroundTopImage="UI/objectives/objectives_barBgLeft.tga"
									BackgroundMidImage="UI/objectives/objectives_barBgMiddle.tga"
									BackgroundBotImage="UI/objectives/objectives_barBgRight.tga"
									InitPopup="rightcenter,leftcenter"
									Tooltip="_999/999"
								>
									<Dummy Name="EventCommunityProgressBg" Height="20" Width="@EventProgressBarLength" MouseSenseEnabled="0"/>
								</FlowContainer>
							<FlowContainer
								MarginLeft="-3"
								MarginTop="8"
								Height="20"
								Horizontal="1"
								BackgroundTopSize="8"
								BackgroundBotSize="8"
								BackgroundTopImage="UI/CharacterSheet/frame_attribute_barLeft.tga"
								BackgroundMidImage="UI/CharacterSheet/frame_attribute_barMiddle.tga"
								BackgroundBotImage="UI/CharacterSheet/frame_attribute_barRight.tga"
								MouseSenseEnabled="0"
							>
								<Dummy Name="EventCommunityProgressBar" Height="20" Width="@EventProgressBarLength" MouseSenseEnabled="0"/>
							</FlowContainer>
							<Container Name="CommunityRewardMarker3" Visible="0">
								<Loop Count="3" Variable="$Y$" Offset="144,0">
									<Image Name="CommunityReward3$Y$Marker"
										Pos="139,26"
										Size="12,12"
										Image="UI/OpenWorld/starmap_barMarker.tga"
										MouseSenseEnabled="0"
									/>
								</Loop>
							</Container>
						</Container>
						<Container Name="EventCommunityMultiProgress" Visible="1">
							<Loop Count="@MultiProgress3" Variable="$X$" Offset="148,0">
								<FlowContainer Name="EventCommunityMultiProgressTooltip$X$"
									MarginTop="8"
									Height="20"
									Horizontal="1"
									BackgroundTopSize="8"
									BackgroundBotSize="8"
									BackgroundTopImage="UI/objectives/objectives_barBgLeft.tga"
									BackgroundMidImage="UI/objectives/objectives_barBgMiddle.tga"
									BackgroundBotImage="UI/objectives/objectives_barBgRight.tga"
									InitPopup="rightcenter,leftcenter"
									Tooltip="_999/999"
								>
									<Dummy Name="EventCommunityMultiProgressBg$X$" Variable="$X$" Height="20" Width="@MultiProgress3Bar" MouseSenseEnabled="0"/>
								</FlowContainer>
								<FlowContainer
									MarginTop="8"
									Height="20"
									Horizontal="1"
									BackgroundTopSize="8"
									BackgroundBotSize="8"
									BackgroundTopImage="UI/CharacterSheet/frame_attribute_barLeft.tga"
									BackgroundMidImage="UI/CharacterSheet/frame_attribute_barMiddle.tga"
									BackgroundBotImage="UI/CharacterSheet/frame_attribute_barRight.tga"
									MouseSenseEnabled="0"
								>
									<Dummy Name="EventCommunityMultiProgressBar$X$" Variable="$X$" Height="20" Width="@MultiProgress3Bar" MouseSenseEnabled="0"/>
								</FlowContainer>
							</Loop>
						</Container>
						<Loop Count="@MaxRewardCount" Variable="$X$">
							<Container Name="CommunityReward$X$" MarginBottom="2" Visible="0">
								<Image Name="CommunityRewardIcon$X$"
									Pos="3,0"
									MarginTop="10"
									Size="45,45"
									Image="UI/common/Events/event_skulls_reward.tga"
									MouseSenseEnabled="0"
								/>	
								<Text Name="CommunityRewardTask$X$"
									Style="Text_Normal_Dark"
									Pos="58,10"
									Size="400,22"
									TextAlignV="center"
									TextAlignH="left"
									Text="_RewardDesc"
									MouseSenseEnabled="0"
								/>
								<Text Name="CommunityRewardReward$X$"
									Style="Text_Normal_Light"
									Pos="58,33"
									Size="400,22"
									TextAlignV="center"
									TextAlignH="left"
									Text="_RewardDesc"
									MouseSenseEnabled="0"
								/>
							</Container>
						</Loop>
					</FlowContainer>						
				</FlowContainer>
			</ScrollableContainer>	
		</Container>
		
		<Text Name="EventDeadline"
			Pos="50,772"
			Size="400,32"
			MarginTop="14"
			Style="Text_Normal_Light"
			Text="_EventDeadline"
			TextAlignH="left"
		/>
		<Icon Name="Ok"
			Pos="809,782"
			Size="160,40"
			IdleImg="UI/Assignment/starmap_panelbuttonOff.tga"
			PressImg="UI/Assignment/starmap_panelbuttonOff.tga"
			RolloverImg="UI/Assignment/starmap_panelbuttonOver.tga"
			Style="Starmap2_3"
			Text="common.ok"
			ShowCategory="mouse"
		/>
		<Icon Name="CabalLeaderboard"
			Pos="489,782"
			Size="160,40"
			IdleImg="UI/Assignment/starmap_panelbuttonOff.tga"
			PressImg="UI/Assignment/starmap_panelbuttonOff.tga"
			RolloverImg="UI/Assignment/starmap_panelbuttonOver.tga"
			Style="Starmap2_3"
			Text="openworld.GUI.worldevent.caballeaderboard"
			ShowCategory="mouse"
		/>
		<Icon Name="Leaderboard"
			Pos="649,782"
			Size="160,40"
			IdleImg="UI/Assignment/starmap_panelbuttonOff.tga"
			PressImg="UI/Assignment/starmap_panelbuttonOff.tga"
			RolloverImg="UI/Assignment/starmap_panelbuttonOver.tga"
			Style="Starmap2_3"
			Text="openworld.GUI.worldevent.leaderboard"
			ShowCategory="mouse"
		/>
		<Icon Name="Close"
			Pos="949,118"
			Size="28,28"
			IdleImg="UI/OpenWorld/icon_closeOff.tga"
			PressImg="UI/OpenWorld/icon_closeOver.tga"
			RolloverImg="UI/OpenWorld/icon_closeOver.tga"
			InitPopup="bottomcenter,topcenter"
			Tooltip="common.close"
			ShowCategory="mouse"
		/>		
	</Container>
	
	
</Window>