<?xml version="1.0" encoding="UTF-8" standalone="yes" ?>
<Window Pos="626,120" GuiAlign="center" OpenTransition="Fast" CloseTransition="Fast">
	<Include Path="Windows/Styles.xml"/>
	
	<Constants>
		<MapShardCount Type="int" Value="9"/>
	</Constants>

	<Image Name="Background"
		Pos="0,0"
		Size="668,800"
		Image="UI/TarotCampaign/PreWindow/TC_Hall_Window_Background.tga"
	/>
	<Image
		Pos="0,0"
		Size="668,800"
		Image="UI/TarotCampaign/PreWindow/TC_Hall_Window_Frame.tga"
	/>
	<Text
		Pos="64,98"
		Size="543,30"
		Style="Headline_Large_Light_Glow"
		TextAlignH="center"
		TextAlignV="center"
		Text="openworld.GUI.voidcrusade.label"
	/>
	<FlowContainer Pos="0,154">
		<TextBox
			MarginLeft="52"
			Width="567"
			Style="Text_Large_Light_Glow"
			TextAlignH="left"
			TextAlignV="top"
			Text="openworld.GUI.voidcrusade.desc"
		/>
		<Container Width="666" MarginLeft="-3" MarginTop="30">
			<FlowContainer Horizontal="1" HAlign="center">
				<Loop Count="@MapShardCount" Variable="$X$">
					<Container Name="MapShardSlot$X$" Size="74,102">
						<Image Name="MapShardSlot$X$Back"
							Size="74,74"
							Image="UI/TarotCampaign/PreWindow/TC_Hall_Window_Map_Shard_Slot_$X$.tga"
						/>
						<Icon Name="MapShardSlot$X$Icon"
							Size="74,74"
							IdleImg="UI/TarotCampaign/PreWindow/TC_Hall_Window_Map_Shard_Slot_$X$_Icons_Base.tga"
							PressImg="UI/TarotCampaign/PreWindow/TC_Hall_Window_Map_Shard_Slot_$X$_Icons_Selected.tga"
							RolloverImg="UI/TarotCampaign/PreWindow/TC_Hall_Window_Map_Shard_Slot_$X$_Icons_Selected.tga"
							UseButtonEffects="0"
							InitPopup="bottomcenter,topcenter"
							ControllerSenseEnabled="1"
						/>
						<Text Name="MapShardSlot$X$Count"
							Pos="7,78"
							Size="60,20"
							Style="GrenadeCharge"
							TextAlignH="center"
							TextAlignV="center"
							Text="99"
							MouseSenseEnabled="0"
						/>
					</Container>
				</Loop>
			</FlowContainer>
			<Container Size="666,40" HAlign="center" MarginTop="110">
				<Image
					Size="323,40"
					Image="UI/TarotCampaign/PreWindow/TC_Hardcore_bg.dds"
					HAlign="center"
				/>
				<CheckBox Name="Hardcore" 
					Text="openworld.GUI.voidcrusade.hardcore"
					Height="32"
					MarginTop="4"
					TextAlignH="center"
					TextAlignV="center"
					Style="Text_Large_Light"
					HAlign="center"
				/>
			</Container>
		</Container>
		
		
		<TextBox Name="Info"
			MarginTop="25"
			MarginLeft="52"
			Width="567"
			Style="Text_Normal_White"
			Color="#ff0000"
			TextAlignH="center"
			TextAlignV="top"
			Text="openworld.GUI.voidcrusade.hint0"
		/>
		

		
		<Icon Name="Create"
			MarginTop="25"
			MarginLeft="230"
			Size="200,48"
			Style="Starmap2_3"
			IdleImg="UI/TarotCampaign/PreWindow/TC_Hall_Window_Create_Map_Buttons_Available.tga"
			PressImg="UI/TarotCampaign/PreWindow/TC_Hall_Window_Create_Map_Buttons_Hover.tga"
			RolloverImg="UI/TarotCampaign/PreWindow/TC_Hall_Window_Create_Map_Buttons_Hover.tga"
			UseButtonEffects="0"
			ShowCategory="mouse"
			Text="openworld.GUI.voidcrusade.createbutton"
		/>
	</FlowContainer>
	
	<Icon Name="Close"
		Pos="623,120"
		Size="28,28"
		IdleImg="UI/OpenWorld/icon_closeOff.tga"
		PressImg="UI/OpenWorld/icon_closeOff.tga"
		RolloverImg="UI/OpenWorld/icon_closeOver.tga"
		InitPopup="bottomcenter,topcenter"
		Tooltip="common.close"
		ShowCategory="mouse"
	/>
	
</Window>